face_dect/__init__.py
face_dect/config_mask.py
face_dect/config_notmask.py
face_dect/example_face_dect.py
face_dect/setup.py
face_dect/test.py
face_dect/Models/CBAM_Face_attention_Resnet_notmaskV3.py
My_face_recognize_ID_Sakura-0.1.0.dist-info/LICENSE
My_face_recognize_ID_Sakura-0.1.0.dist-info/METADATA
My_face_recognize_ID_Sakura-0.1.0.dist-info/WHEEL
My_face_recognize_ID_Sakura-0.1.0.dist-info/top_level.txt
My_face_recognize_ID_Sakura-0.1.0.dist-info/RECORD
