Metadata-Version: 2.1
Name: My-face-recognize-ID-Sakura
Version: 0.1.0
Summary: A small example package to detect face
Home-page: https://blog.csdn.net/Sakura_day?spm=1004.2022.3001.5343
Author: Sakura
Author-email: author@example.com
License: UNKNOWN
Platform: UNKNOWN
Classifier: Programming Language :: Python :: 3
Classifier: License :: OSI Approved :: MIT License
Classifier: Operating System :: OS Independent
Requires-Python: >=3.6
